gtrick/__init__.py
gtrick/fingerprint.py
gtrick/flag.py
gtrick/random_feature.py
gtrick/dgl/__init__.py
gtrick/dgl/correct_and_smooth.py
gtrick/dgl/edge_feat.py
gtrick/dgl/label_prop.py
gtrick/dgl/virtual_node.py
gtrick/pyg/__init__.py
gtrick/pyg/edge_feat.py
gtrick/pyg/virtual_node.py
gtrick-0.0.dev2.dist-info/LICENSE
gtrick-0.0.dev2.dist-info/METADATA
gtrick-0.0.dev2.dist-info/WHEEL
gtrick-0.0.dev2.dist-info/top_level.txt
gtrick-0.0.dev2.dist-info/RECORD
