Metadata-Version: 2.1
Name: gtrick
Version: 0.0.dev2
Summary: Bag of Tricks for Graph Neural Networks
Home-page: https://github.com/sangyx/gtrick
Author: sangyx
Author-email: sangyunxin@gmail.com
License: UNKNOWN
Platform: UNKNOWN
Classifier: Programming Language :: Python :: 3
Classifier: License :: OSI Approved :: MIT License
Classifier: Operating System :: OS Independent
Requires-Python: >=3
License-File: LICENSE
Requires-Dist: torch
Requires-Dist: numpy
Requires-Dist: networkx
